{
  "pipeline": {
    "name": "EnterpriseDeploymentPipeline",
    "roleArn": "arn:aws:iam::ACCOUNT_ID:role/CodePipelineServiceRole",
    "artifactStore": {
      "type": "S3",
      "location": "codepipeline-artifacts-bucket"
    },
    "stages": [
      {
        "name": "Source",
        "actions": [
          {
            "name": "Source",
            "actionTypeId": {
              "category": "Source",
              "owner": "ThirdParty",
              "provider": "GitHub",
              "version": "1"
            },
            "outputArtifacts": [ { "name": "SourceArtifact" } ],
            "configuration": {
              "Owner": "mallagarisridatta",
              "Repo": "fullstack-app-terraform-aws",
              "Branch": "main",
              "OAuthToken": "****"
            }
          }
        ]
      },
      {
        "name": "Build-and-Deploy-Infra",
        "actions": [
          {
            "name": "TerraformApply",
            "actionTypeId": {
              "category": "Build",
              "owner": "AWS",
              "provider": "CodeBuild",
              "version": "1"
            },
            "inputArtifacts": [ { "name": "SourceArtifact" } ],
            "configuration": {
              "ProjectName": "TerraformBuildProject"
            }
          }
        ]
      }
    ]
  }
}